LICENSE
README.md
setup.py
qlv_client/__init__.py
qlv_client/api.py
qlv_client/config.py
qlv_client/converter.py
qlv_client/http_client.py
qlv_client/proxy.py
qlv_client/repository.py
qlv_client/test.py
qlv_client/utils.py
qlv_client.egg-info/PKG-INFO
qlv_client.egg-info/SOURCES.txt
qlv_client.egg-info/dependency_links.txt
qlv_client.egg-info/requires.txt
qlv_client.egg-info/top_level.txt