Metadata-Version: 2.1
Name: qlv-client
Version: 0.1.3
Summary: This is my qlv proxy qlv_client package
Home-page: https://github.com/ckf10000/qlvClient
Author: ckf10000
Author-email: ckf10000@sina.com
Classifier: Programming Language :: Python :: 3
Classifier: License :: OSI Approved :: MIT License
Classifier: Operating System :: OS Independent
License-File: LICENSE
Requires-Dist: requests>=2.31.0
